{
    "0": [
        {
            "keyword": "Id Number",
            "coordinates": [
                {
                    "x0": 35,
                    "y0": 199.125,
                    "x1": 134,
                    "y1": 340.125
                }
            ]
        },
        {
            "keyword": "Item Description",
            "coordinates": [
                {
                    "x0": 201,
                    "y0": 195.125,
                    "x1": 439,
                    "y1": 431.125
                }
            ]
        },
        {
            "keyword": "SWL",
            "coordinates": [
                {
                    "x0": 446,
                    "y0": 197.125,
                    "x1": 492,
                    "y1": 304.125
                }
            ]
        },
        {
            "keyword": "Certificate No",
            "coordinates": [
                {
                    "x0": 402,
                    "y0": 16.125,
                    "x1": 477,
                    "y1": 36.125
                }
            ]
        },
        {
            "keyword": "Previous Inspection",
            "coordinates": [
                {
                    "x0": 400,
                    "y0": 79.125,
                    "x1": 500,
                    "y1": 95.125
                }
            ]
        },
        {
            "keyword": "Next Inspection Due Date",
            "coordinates": [
                {
                    "x0": 400,
                    "y0": 94.125,
                    "x1": 484,
                    "y1": 113.125
                }
            ]
        }
    ],
    "1": [
        {
            "keyword": "Id Number",
            "coordinates": [
                {
                    "x0": 35,
                    "y0": 199.125,
                    "x1": 134,
                    "y1": 340.125
                }
            ]
        },
        {
            "keyword": "Item Description",
            "coordinates": [
                {
                    "x0": 201,
                    "y0": 195.125,
                    "x1": 439,
                    "y1": 431.125
                }
            ]
        },
        {
            "keyword": "SWL",
            "coordinates": [
                {
                    "x0": 446,
                    "y0": 197.125,
                    "x1": 492,
                    "y1": 304.125
                }
            ]
        },
        {
            "keyword": "Certificate No",
            "coordinates": [
                {
                    "x0": 402,
                    "y0": 16.125,
                    "x1": 477,
                    "y1": 36.125
                }
            ]
        },
        {
            "keyword": "Previous Inspection",
            "coordinates": [
                {
                    "x0": 400,
                    "y0": 79.125,
                    "x1": 500,
                    "y1": 95.125
                }
            ]
        },
        {
            "keyword": "Next Inspection Due Date",
            "coordinates": [
                {
                    "x0": 400,
                    "y0": 94.125,
                    "x1": 484,
                    "y1": 113.125
                }
            ]
        }
    ],
    "2": [
        {
            "keyword": "Id Number",
            "coordinates": [
                {
                    "x0": 35,
                    "y0": 199.125,
                    "x1": 134,
                    "y1": 340.125
                }
            ]
        },
        {
            "keyword": "Item Description",
            "coordinates": [
                {
                    "x0": 201,
                    "y0": 195.125,
                    "x1": 439,
                    "y1": 431.125
                }
            ]
        },
        {
            "keyword": "SWL",
            "coordinates": [
                {
                    "x0": 446,
                    "y0": 197.125,
                    "x1": 492,
                    "y1": 304.125
                }
            ]
        },
        {
            "keyword": "Certificate No",
            "coordinates": [
                {
                    "x0": 402,
                    "y0": 16.125,
                    "x1": 477,
                    "y1": 36.125
                }
            ]
        },
        {
            "keyword": "Previous Inspection",
            "coordinates": [
                {
                    "x0": 400,
                    "y0": 79.125,
                    "x1": 500,
                    "y1": 95.125
                }
            ]
        },
        {
            "keyword": "Next Inspection Due Date",
            "coordinates": [
                {
                    "x0": 400,
                    "y0": 94.125,
                    "x1": 484,
                    "y1": 113.125
                }
            ]
        }
    ],
    "3": [
        {
            "keyword": "Id Number",
            "coordinates": [
                {
                    "x0": 35,
                    "y0": 199.125,
                    "x1": 134,
                    "y1": 340.125
                }
            ]
        },
        {
            "keyword": "Item Description",
            "coordinates": [
                {
                    "x0": 201,
                    "y0": 195.125,
                    "x1": 439,
                    "y1": 431.125
                }
            ]
        },
        {
            "keyword": "SWL",
            "coordinates": [
                {
                    "x0": 446,
                    "y0": 197.125,
                    "x1": 492,
                    "y1": 304.125
                }
            ]
        },
        {
            "keyword": "Certificate No",
            "coordinates": [
                {
                    "x0": 402,
                    "y0": 16.125,
                    "x1": 477,
                    "y1": 36.125
                }
            ]
        },
        {
            "keyword": "Previous Inspection",
            "coordinates": [
                {
                    "x0": 400,
                    "y0": 79.125,
                    "x1": 500,
                    "y1": 95.125
                }
            ]
        },
        {
            "keyword": "Next Inspection Due Date",
            "coordinates": [
                {
                    "x0": 400,
                    "y0": 94.125,
                    "x1": 484,
                    "y1": 113.125
                }
            ]
        }
    ],
    "4": [
        {
            "keyword": "Id Number",
            "coordinates": [
                {
                    "x0": 35,
                    "y0": 199.125,
                    "x1": 134,
                    "y1": 340.125
                }
            ]
        },
        {
            "keyword": "Item Description",
            "coordinates": [
                {
                    "x0": 201,
                    "y0": 195.125,
                    "x1": 439,
                    "y1": 431.125
                }
            ]
        },
        {
            "keyword": "SWL",
            "coordinates": [
                {
                    "x0": 446,
                    "y0": 197.125,
                    "x1": 492,
                    "y1": 304.125
                }
            ]
        },
        {
            "keyword": "Certificate No",
            "coordinates": [
                {
                    "x0": 402,
                    "y0": 16.125,
                    "x1": 477,
                    "y1": 36.125
                }
            ]
        },
        {
            "keyword": "Previous Inspection",
            "coordinates": [
                {
                    "x0": 400,
                    "y0": 79.125,
                    "x1": 500,
                    "y1": 95.125
                }
            ]
        },
        {
            "keyword": "Next Inspection Due Date",
            "coordinates": [
                {
                    "x0": 400,
                    "y0": 94.125,
                    "x1": 484,
                    "y1": 113.125
                }
            ]
        }
    ],
    "5": [
        {
            "keyword": "Id Number",
            "coordinates": [
                {
                    "x0": 35,
                    "y0": 199.125,
                    "x1": 134,
                    "y1": 340.125
                }
            ]
        },
        {
            "keyword": "Item Description",
            "coordinates": [
                {
                    "x0": 201,
                    "y0": 195.125,
                    "x1": 439,
                    "y1": 431.125
                }
            ]
        },
        {
            "keyword": "SWL",
            "coordinates": [
                {
                    "x0": 446,
                    "y0": 197.125,
                    "x1": 492,
                    "y1": 304.125
                }
            ]
        },
        {
            "keyword": "Certificate No",
            "coordinates": [
                {
                    "x0": 402,
                    "y0": 16.125,
                    "x1": 477,
                    "y1": 36.125
                }
            ]
        },
        {
            "keyword": "Previous Inspection",
            "coordinates": [
                {
                    "x0": 400,
                    "y0": 79.125,
                    "x1": 500,
                    "y1": 95.125
                }
            ]
        },
        {
            "keyword": "Next Inspection Due Date",
            "coordinates": [
                {
                    "x0": 400,
                    "y0": 94.125,
                    "x1": 484,
                    "y1": 113.125
                }
            ]
        }
    ],
    "6": [
        {
            "keyword": "Id Number",
            "coordinates": [
                {
                    "x0": 35,
                    "y0": 199.125,
                    "x1": 134,
                    "y1": 340.125
                }
            ]
        },
        {
            "keyword": "Item Description",
            "coordinates": [
                {
                    "x0": 201,
                    "y0": 195.125,
                    "x1": 439,
                    "y1": 431.125
                }
            ]
        },
        {
            "keyword": "SWL",
            "coordinates": [
                {
                    "x0": 446,
                    "y0": 197.125,
                    "x1": 492,
                    "y1": 304.125
                }
            ]
        },
        {
            "keyword": "Certificate No",
            "coordinates": [
                {
                    "x0": 402,
                    "y0": 16.125,
                    "x1": 477,
                    "y1": 36.125
                }
            ]
        },
        {
            "keyword": "Previous Inspection",
            "coordinates": [
                {
                    "x0": 400,
                    "y0": 79.125,
                    "x1": 500,
                    "y1": 95.125
                }
            ]
        },
        {
            "keyword": "Next Inspection Due Date",
            "coordinates": [
                {
                    "x0": 400,
                    "y0": 94.125,
                    "x1": 484,
                    "y1": 113.125
                }
            ]
        }
    ],
    "7": [
        {
            "keyword": "Id Number",
            "coordinates": [
                {
                    "x0": 35,
                    "y0": 199.125,
                    "x1": 134,
                    "y1": 340.125
                }
            ]
        },
        {
            "keyword": "Item Description",
            "coordinates": [
                {
                    "x0": 201,
                    "y0": 195.125,
                    "x1": 439,
                    "y1": 431.125
                }
            ]
        },
        {
            "keyword": "SWL",
            "coordinates": [
                {
                    "x0": 446,
                    "y0": 197.125,
                    "x1": 492,
                    "y1": 304.125
                }
            ]
        },
        {
            "keyword": "Certificate No",
            "coordinates": [
                {
                    "x0": 402,
                    "y0": 16.125,
                    "x1": 477,
                    "y1": 36.125
                }
            ]
        },
        {
            "keyword": "Previous Inspection",
            "coordinates": [
                {
                    "x0": 400,
                    "y0": 79.125,
                    "x1": 500,
                    "y1": 95.125
                }
            ]
        },
        {
            "keyword": "Next Inspection Due Date",
            "coordinates": [
                {
                    "x0": 400,
                    "y0": 94.125,
                    "x1": 484,
                    "y1": 113.125
                }
            ]
        }
    ],
    "8": [
        {
            "keyword": "Id Number",
            "coordinates": [
                {
                    "x0": 35,
                    "y0": 199.125,
                    "x1": 134,
                    "y1": 340.125
                }
            ]
        },
        {
            "keyword": "Item Description",
            "coordinates": [
                {
                    "x0": 201,
                    "y0": 195.125,
                    "x1": 439,
                    "y1": 431.125
                }
            ]
        },
        {
            "keyword": "SWL",
            "coordinates": [
                {
                    "x0": 446,
                    "y0": 197.125,
                    "x1": 492,
                    "y1": 304.125
                }
            ]
        },
        {
            "keyword": "Certificate No",
            "coordinates": [
                {
                    "x0": 402,
                    "y0": 16.125,
                    "x1": 477,
                    "y1": 36.125
                }
            ]
        },
        {
            "keyword": "Previous Inspection",
            "coordinates": [
                {
                    "x0": 400,
                    "y0": 79.125,
                    "x1": 500,
                    "y1": 95.125
                }
            ]
        },
        {
            "keyword": "Next Inspection Due Date",
            "coordinates": [
                {
                    "x0": 400,
                    "y0": 94.125,
                    "x1": 484,
                    "y1": 113.125
                }
            ]
        }
    ],
    "9": [
        {
            "keyword": "Id Number",
            "coordinates": [
                {
                    "x0": 35,
                    "y0": 199.125,
                    "x1": 134,
                    "y1": 340.125
                }
            ]
        },
        {
            "keyword": "Item Description",
            "coordinates": [
                {
                    "x0": 201,
                    "y0": 195.125,
                    "x1": 439,
                    "y1": 431.125
                }
            ]
        },
        {
            "keyword": "SWL",
            "coordinates": [
                {
                    "x0": 446,
                    "y0": 197.125,
                    "x1": 492,
                    "y1": 304.125
                }
            ]
        },
        {
            "keyword": "Certificate No",
            "coordinates": [
                {
                    "x0": 402,
                    "y0": 16.125,
                    "x1": 477,
                    "y1": 36.125
                }
            ]
        },
        {
            "keyword": "Previous Inspection",
            "coordinates": [
                {
                    "x0": 400,
                    "y0": 79.125,
                    "x1": 500,
                    "y1": 95.125
                }
            ]
        },
        {
            "keyword": "Next Inspection Due Date",
            "coordinates": [
                {
                    "x0": 400,
                    "y0": 94.125,
                    "x1": 484,
                    "y1": 113.125
                }
            ]
        }
    ]
}